Workbook

Sheet SKU Catalog
A1: PRIVATE AI OPS
A2: SKU & Pricing Catalog
A3: Master service/product list — September 2026
A5: SKU Code | B5: Product / Service Name | C5: Category | D5: Applicable Vertical(s) | E5: Pricing Type | F5: Price – Low | G5: Price – High | H5: Billing Unit / Cadence | I5: Typical Client Profile | J5: Notes
A6: PAO-ASM-STD | B6: AI Ops Assessment (Standard) | C6: Assessment | D6: All verticals | E6: One-time | F6: 500 | G6: 1500 | H6: One-time, due at engagement start | I6: Single-location SMB, straightforward workflow scope | J6: Waived if client signs Managed Onboarding within 30 days
A7: PAO-ASM-CPX | B7: AI Ops Assessment (Complex / Regulated) | C7: Assessment | D7: Law, Dental/Healthcare | E7: One-time | F7: 1500 | G7: 2500 | H7: One-time, due at engagement start | I7: Multi-location or regulated-vertical SMB | J7: Waived if client signs Managed Onboarding within 30 days
A8: PAO-ONB-SM | B8: Managed AI Onboarding (Small SMB) | C8: Onboarding | D8: All verticals | E8: One-time | F8: 3500 | G8: 10000 | H8: One-time, milestone or 50/50 split | I8: Single-location SMB, 1–3 workflows in scope | J8: Entry gate into the managed retainer relationship
A9: PAO-ONB-CPX | B9: Managed AI Onboarding (Complex / Regulated) | C9: Onboarding | D9: Law, Dental/Healthcare, Property Mgmt | E9: One-time | F9: 10000 | G9: 25000 | H9: One-time, milestone or 50/50 split | I9: Multi-location, regulated, or multi-workflow SMB | J9: Includes BAA/DPA execution, security/access configuration
A10: PAO-RET-SM | B10: Managed AI Ops Retainer (Small SMB) | C10: Retainer | D10: All verticals | E10: Recurring | F10: 1500 | G10: 3000 | H10: Monthly, auto-billed | I10: Single-location SMB, 1–2 active workflows | J10: Core recurring revenue line
A11: PAO-RET-MX | B11: Managed AI Ops Retainer (Multi-location / Regulated) | C11: Retainer | D11: Law, Dental/Healthcare, Property Mgmt | E11: Recurring | F11: 3000 | G11: 7500 | H11: Monthly, auto-billed | I11: Multi-location or regulated SMB, 3+ active workflows | J11: Includes governance updates, usage analytics
A12: PAO-RET-HV | B12: Managed AI Ops Retainer (Heavy / Custom Environment) | C12: Retainer | D12: All verticals | E12: Recurring | F12: 7500 | G12: 12000 | H12: Monthly, auto-billed | I12: Complex multi-workflow environment or heavy infra usage | J12: Paired with a Private AI Infrastructure add-on in most cases
A13: PAO-INF-END | B13: Private AI Infrastructure — Private Endpoint | C13: Infrastructure Add-on | D13: All verticals | E13: Recurring add-on | F13: 650 | G13: 650 | H13: Monthly, add-on to Retainer | I13: Client needs isolated inference, not full HIPAA scope | J13: Not sold standalone — requires an active Retainer
A14: PAO-INF-BAA | B14: Private AI Infrastructure — HIPAA-Ready / BAA-Supported Endpoint | C14: Infrastructure Add-on | D14: Dental/Healthcare, Law | E14: Recurring add-on | F14: 850 | G14: 850 | H14: Monthly, add-on to Retainer | I14: Client requires BAA-supported, audit-friendly endpoint | J14: Legal template execution required before activation
A15: PAO-INF-RAG | B15: Private AI Infrastructure — Dual GPU + RAG | C15: Infrastructure Add-on | D15: Law, Property Mgmt | E15: Recurring add-on | F15: 1400 | G15: 1400 | H15: Monthly, add-on to Retainer | I15: Document-heavy workflows needing dedicated retrieval | J15: Requires Phase 2 GPU infrastructure to be deployed
A16: PAO-INF-MGD | B16: Private AI Infrastructure — Managed Private AI Environment | C16: Infrastructure Add-on | D16: All verticals | E16: Recurring add-on | F16: 2200 | G16: 3500 | H16: Monthly, add-on to Retainer | I16: Enterprise-leaning SMB or multi-entity client | J16: Highest infra tier; scope and price set case-by-case above range
A17: PAO-FREE-LAW | B17: Law Brief — Intake Summary / Case Chronology Generator | C17: Free Tool | D17: Law | E17: Free | F17: 0 | G17: 0 | H17: N/A — lead generation | I17: Prospective law firm client, top of funnel | J17: Distribution and qualification tool, not a revenue SKU
... A21: PAO-PRO-STD | B21: Pro Tier Subscription | C21: Validation Tier | D21: All verticals (per free-tool app) | E21: Recurring | F21: 49 | G21: 199 | H21: Monthly, self-serve billing | I21: High-intent free-tool user not yet ready for a retainer | J21: Validation layer, not the primary revenue engine
A23: Legend:
A24: Blue text = hardcoded price input
A25: Prices are current list pricing as of Sept 2026 — confirm before quoting a specific client.

Sheet Vertical Packages
A1: PRIVATE AI OPS
A2: Recommended Vertical Packages
A3: Bundled SKUs by vertical, with Year-1 contract value estimate
A5: Vertical | B5: Package | C5: Included SKUs | D5: Onboarding SKU | E5: Onboarding Low | F5: Onboarding High | G5: Retainer SKU | H5: Retainer Low (mo) | I5: Retainer High (mo) | J5: Infra Add-on SKU | K5: Infra Low (mo) | L5: Infra High (mo) | M5: Est. Year-1 TCV – Low | N5: Est. Year-1 TCV – High
A6: Law Firms | B6: Starter | C6: PAO-ONB-SM + PAO-RET-SM | D6: PAO-ONB-SM | E6: =INDEX('SKU Catalog'!$F$6:$F$21,MATCH(D6,'SKU Catalog'!$A$6:$A$21,0)) -> 3500 | F6: =INDEX('SKU Catalog'!$G$6:$G$21,MATCH(D6,'SKU Catalog'!$A$6:$A$21,0)) -> 10000 | G6: PAO-RET-SM | H6: =INDEX('SKU Catalog'!$F$6:$F$21,MATCH(G6,'SKU Catalog'!$A$6:$A$21,0)) -> 1500 | I6: =INDEX('SKU Catalog'!$G$6:$G$21,MATCH(G6,'SKU Catalog'!$A$6:$A$21,0)) -> 3000 | J6: — | K6: 0 | L6: 0 | M6: =E6+(H6+K6)*12 -> 21500 | N6: =F6+(I6+L6)*12 -> 46000
A7: Law Firms | B7: Growth (Privilege-Sensitive) | C7: PAO-ONB-CPX + PAO-RET-MX + PAO-INF-END | D7: PAO-ONB-CPX | E7: =INDEX('SKU Catalog'!$F$6:$F$21,MATCH(D7,'SKU Catalog'!$A$6:$A$21,0)) -> 10000 | F7: =INDEX('SKU Catalog'!$G$6:$G$21,MATCH(D7,'SKU Catalog'!$A$6:$A$21,0)) -> 25000 | G7: PAO-RET-MX | H7: =INDEX('SKU Catalog'!$F$6:$F$21,MATCH(G7,'SKU Catalog'!$A$6:$A$21,0)) -> 3000 | I7: =INDEX('SKU Catalog'!$G$6:$G$21,MATCH(G7,'SKU Catalog'!$A$6:$A$21,0)) -> 7500 | J7: PAO-INF-END | K7: =INDEX('SKU Catalog'!$F$6:$F$21,MATCH(J7,'SKU Catalog'!$A$6:$A$21,0)) -> 650 | L7: =INDEX('SKU Catalog'!$G$6:$G$21,MATCH(J7,'SKU Catalog'!$A$6:$A$21,0)) -> 650 | M7: =E7+(H7+K7)*12 -> 53800 | N7: =F7+(I7+L7)*12 -> 122800
A8: Dental / Healthcare | B8: Starter | C8: PAO-ONB-SM + PAO-RET-SM | D8: PAO-ONB-SM | E8: =INDEX('SKU Catalog'!$F$6:$F$21,MATCH(D8,'SKU Catalog'!$A$6:$A$21,0)) -> 3500 | F8: =INDEX('SKU Catalog'!$G$6:$G$21,MATCH(D8,'SKU Catalog'!$A$6:$A$21,0)) -> 10000 | G8: PAO-RET-SM | H8: =INDEX('SKU Catalog'!$F$6:$F$21,MATCH(G8,'SKU Catalog'!$A$6:$A$21,0)) -> 1500 | I8: =INDEX('SKU Catalog'!$G$6:$G$21,MATCH(G8,'SKU Catalog'!$A$6:$A$21,0)) -> 3000 | J8: — | K8: 0 | L8: 0 | M8: =E8+(H8+K8)*12 -> 21500 | N8: =F8+(I8+L8)*12 -> 46000
A9: Dental / Healthcare | B9: Growth (HIPAA-Ready) | C9: PAO-ONB-CPX + PAO-RET-MX + PAO-INF-BAA | D9: PAO-ONB-CPX | E9: =INDEX('SKU Catalog'!$F$6:$F$21,MATCH(D9,'SKU Catalog'!$A$6:$A$21,0)) -> 10000 | F9: =INDEX('SKU Catalog'!$G$6:$G$21,MATCH(D9,'SKU Catalog'!$A$6:$A$21,0)) -> 25000 | G9: PAO-RET-MX | H9: =INDEX('SKU Catalog'!$F$6:$F$21,MATCH(G9,'SKU Catalog'!$A$6:$A$21,0)) -> 3000 | I9: =INDEX('SKU Catalog'!$G$6:$G$21,MATCH(G9,'SKU Catalog'!$A$6:$A$21,0)) -> 7500 | J9: PAO-INF-BAA | K9: =INDEX('SKU Catalog'!$F$6:$F$21,MATCH(J9,'SKU Catalog'!$A$6:$A$21,0)) -> 850 | L9: =INDEX('SKU Catalog'!$G$6:$G$21,MATCH(J9,'SKU Catalog'!$A$6:$A$21,0)) -> 850 | M9: =E9+(H9+K9)*12 -> 56200 | N9: =F9+(I9+L9)*12 -> 125200
A10: Property Management | B10: Starter | C10: PAO-ONB-SM + PAO-RET-SM | D10: PAO-ONB-SM | E10: =INDEX('SKU Catalog'!$F$6:$F$21,MATCH(D10,'SKU Catalog'!$A$6:$A$21,0)) -> 3500 | F10: =INDEX('SKU Catalog'!$G$6:$G$21,MATCH(D10,'SKU Catalog'!$A$6:$A$21,0)) -> 10000 | G10: PAO-RET-SM | H10: =INDEX('SKU Catalog'!$F$6:$F$21,MATCH(G10,'SKU Catalog'!$A$6:$A$21,0)) -> 1500 | I10: =INDEX('SKU Catalog'!$G$6:$G$21,MATCH(G10,'SKU Catalog'!$A$6:$A$21,0)) -> 3000 | J10: — | K10: 0 | L10: 0 | M10: =E10+(H10+K10)*12 -> 21500 | N10: =F10+(I10+L10)*12 -> 46000
A11: Property Management | B11: Growth (Portfolio Scale) | C11: PAO-ONB-CPX + PAO-RET-MX + PAO-INF-RAG | D11: PAO-ONB-CPX | E11: =INDEX('SKU Catalog'!$F$6:$F$21,MATCH(D11,'SKU Catalog'!$A$6:$A$21,0)) -> 10000 | F11: =INDEX('SKU Catalog'!$G$6:$G$21,MATCH(D11,'SKU Catalog'!$A$6:$A$21,0)) -> 25000 | G11: PAO-RET-MX | H11: =INDEX('SKU Catalog'!$F$6:$F$21,MATCH(G11,'SKU Catalog'!$A$6:$A$21,0)) -> 3000 | I11: =INDEX('SKU Catalog'!$G$6:$G$21,MATCH(G11,'SKU Catalog'!$A$6:$A$21,0)) -> 7500 | J11: PAO-INF-RAG | K11: =INDEX('SKU Catalog'!$F$6:$F$21,MATCH(J11,'SKU Catalog'!$A$6:$A$21,0)) -> 1400 | L11: =INDEX('SKU Catalog'!$G$6:$G$21,MATCH(J11,'SKU Catalog'!$A$6:$A$21,0)) -> 1400 | M11: =E11+(H11+K11)*12 -> 62800 | N11: =F11+(I11+L11)*12 -> 131800
A12: Marine / Charter | B12: Starter | C12: PAO-ONB-SM + PAO-RET-SM | D12: PAO-ONB-SM | E12: =INDEX('SKU Catalog'!$F$6:$F$21,MATCH(D12,'SKU Catalog'!$A$6:$A$21,0)) -> 3500 | F12: =INDEX('SKU Catalog'!$G$6:$G$21,MATCH(D12,'SKU Catalog'!$A$6:$A$21,0)) -> 10000 | G12: PAO-RET-SM | H12: =INDEX('SKU Catalog'!$F$6:$F$21,MATCH(G12,'SKU Catalog'!$A$6:$A$21,0)) -> 1500 | I12: =INDEX('SKU Catalog'!$G$6:$G$21,MATCH(G12,'SKU Catalog'!$A$6:$A$21,0)) -> 3000 | J12: — | K12: 0 | L12: 0 | M12: =E12+(H12+K12)*12 -> 21500 | N12: =F12+(I12+L12)*12 -> 46000
A13: Marine / Charter | B13: Growth (Multi-Vessel) | C13: PAO-ONB-CPX + PAO-RET-MX | D13: PAO-ONB-CPX | E13: =INDEX('SKU Catalog'!$F$6:$F$21,MATCH(D13,'SKU Catalog'!$A$6:$A$21,0)) -> 10000 | F13: =INDEX('SKU Catalog'!$G$6:$G$21,MATCH(D13,'SKU Catalog'!$A$6:$A$21,0)) -> 25000 | G13: PAO-RET-MX | H13: =INDEX('SKU Catalog'!$F$6:$F$21,MATCH(G13,'SKU Catalog'!$A$6:$A$21,0)) -> 3000 | I13: =INDEX('SKU Catalog'!$G$6:$G$21,MATCH(G13,'SKU Catalog'!$A$6:$A$21,0)) -> 7500 | J13: — | K13: 0 | L13: 0 | M13: =E13+(H13+K13)*12 -> 46000 | N13: =F13+(I13+L13)*12 -> 115000
A15: Est. Year-1 TCV = Onboarding fee + (monthly Retainer + monthly Infra add-on) × 12. Green cells are formulas pulling live prices from the SKU Catalog tab — update prices there, not here.

Sheet Margin Reference
A1: PRIVATE AI OPS
A2: Directional Margin Reference by SKU Category
A3: Assumption-based — replace with actual time-tracking once operating
A5: SKU Code | B5: Category | C5: Price (midpoint) | D5: Est. Delivery Hours | E5: Blended Labor Rate ($/hr) | F5: Labor Cost | G5: Est. Monthly/One-Time COGS (API + tooling) | H5: Total Cost | I5: Gross Margin ($) | J5: Gross Margin (%)
A6: PAO-ASM-STD | B6: =INDEX('SKU Catalog'!$C$6:$C$21,MATCH(A6,'SKU Catalog'!$A$6:$A$21,0)) -> Assessment | C6: =AVERAGE(INDEX('SKU Catalog'!$F$6:$F$21,MATCH(A6,'SKU Catalog'!$A$6:$A$21,0)),INDEX('SKU Catalog'!$G$6:$G$21,MATCH(A6,'SKU Catalog'!$A$6:$A$21,0))) -> 1000 | D6: 8 | E6: 75 | F6: =D6*E6 -> 600 | G6: 15 | H6: =F6+G6 -> 615 | I6: =C6-H6 -> 385 | J6: =IFERROR(I6/C6,0) -> 0.385
A7: PAO-ASM-CPX | B7: =INDEX('SKU Catalog'!$C$6:$C$21,MATCH(A7,'SKU Catalog'!$A$6:$A$21,0)) -> Assessment | C7: =AVERAGE(INDEX('SKU Catalog'!$F$6:$F$21,MATCH(A7,'SKU Catalog'!$A$6:$A$21,0)),INDEX('SKU Catalog'!$G$6:$G$21,MATCH(A7,'SKU Catalog'!$A$6:$A$21,0))) -> 2000 | D7: 14 | E7: 75 | F7: =D7*E7 -> 1050 | G7: 25 | H7: =F7+G7 -> 1075 | I7: =C7-H7 -> 925 | J7: =IFERROR(I7/C7,0) -> 0.4625
A8: PAO-ONB-SM | B8: =INDEX('SKU Catalog'!$C$6:$C$21,MATCH(A8,'SKU Catalog'!$A$6:$A$21,0)) -> Onboarding | C8: =AVERAGE(INDEX('SKU Catalog'!$F$6:$F$21,MATCH(A8,'SKU Catalog'!$A$6:$A$21,0)),INDEX('SKU Catalog'!$G$6:$G$21,MATCH(A8,'SKU Catalog'!$A$6:$A$21,0))) -> 6750 | D8: 25 | E8: 75 | F8: =D8*E8 -> 1875 | G8: 40 | H8: =F8+G8 -> 1915 | I8: =C8-H8 -> 4835 | J8: =IFERROR(I8/C8,0) -> 0.7162963
A9: PAO-ONB-CPX | B9: =INDEX('SKU Catalog'!$C$6:$C$21,MATCH(A9,'SKU Catalog'!$A$6:$A$21,0)) -> Onboarding | C9: =AVERAGE(INDEX('SKU Catalog'!$F$6:$F$21,MATCH(A9,'SKU Catalog'!$A$6:$A$21,0)),INDEX('SKU Catalog'!$G$6:$G$21,MATCH(A9,'SKU Catalog'!$A$6:$A$21,0))) -> 17500 | D9: 55 | E9: 75 | F9: =D9*E9 -> 4125 | G9: 100 | H9: =F9+G9 -> 4225 | I9: =C9-H9 -> 13275 | J9: =IFERROR(I9/C9,0) -> 0.75857143
A10: PAO-RET-SM | B10: =INDEX('SKU Catalog'!$C$6:$C$21,MATCH(A10,'SKU Catalog'!$A$6:$A$21,0)) -> Retainer | C10: =AVERAGE(INDEX('SKU Catalog'!$F$6:$F$21,MATCH(A10,'SKU Catalog'!$A$6:$A$21,0)),INDEX('SKU Catalog'!$G$6:$G$21,MATCH(A10,'SKU Catalog'!$A$6:$A$21,0))) -> 2250 | D10: 6 | E10: 75 | F10: =D10*E10 -> 450 | G10: 15 | H10: =F10+G10 -> 465 | I10: =C10-H10 -> 1785 | J10: =IFERROR(I10/C10,0) -> 0.79333333
A11: PAO-RET-MX | B11: =INDEX('SKU Catalog'!$C$6:$C$21,MATCH(A11,'SKU Catalog'!$A$6:$A$21,0)) -> Retainer | C11: =AVERAGE(INDEX('SKU Catalog'!$F$6:$F$21,MATCH(A11,'SKU Catalog'!$A$6:$A$21,0)),INDEX('SKU Catalog'!$G$6:$G$21,MATCH(A11,'SKU Catalog'!$A$6:$A$21,0))) -> 5250 | D11: 12 | E11: 75 | F11: =D11*E11 -> 900 | G11: 40 | H11: =F11+G11 -> 940 | I11: =C11-H11 -> 4310 | J11: =IFERROR(I11/C11,0) -> 0.82095238
A12: PAO-RET-HV | B12: =INDEX('SKU Catalog'!$C$6:$C$21,MATCH(A12,'SKU Catalog'!$A$6:$A$21,0)) -> Retainer | C12: =AVERAGE(INDEX('SKU Catalog'!$F$6:$F$21,MATCH(A12,'SKU Catalog'!$A$6:$A$21,0)),INDEX('SKU Catalog'!$G$6:$G$21,MATCH(A12,'SKU Catalog'!$A$6:$A$21,0))) -> 9750 | D12: 20 | E12: 75 | F12: =D12*E12 -> 1500 | G12: 80 | H12: =F12+G12 -> 1580 | I12: =C12-H12 -> 8170 | J12: =IFERROR(I12/C12,0) -> 0.83794872
A13: PAO-INF-END | B13: =INDEX('SKU Catalog'!$C$6:$C$21,MATCH(A13,'SKU Catalog'!$A$6:$A$21,0)) -> Infrastructure Add-on | C13: =AVERAGE(INDEX('SKU Catalog'!$F$6:$F$21,MATCH(A13,'SKU Catalog'!$A$6:$A$21,0)),INDEX('SKU Catalog'!$G$6:$G$21,MATCH(A13,'SKU Catalog'!$A$6:$A$21,0))) -> 650 | D13: 2 | E13: 75 | F13: =D13*E13 -> 150 | G13: 90 | H13: =F13+G13 -> 240 | I13: =C13-H13 -> 410 | J13: =IFERROR(I13/C13,0) -> 0.63076923
A14: PAO-INF-BAA | B14: =INDEX('SKU Catalog'!$C$6:$C$21,MATCH(A14,'SKU Catalog'!$A$6:$A$21,0)) -> Infrastructure Add-on | C14: =AVERAGE(INDEX('SKU Catalog'!$F$6:$F$21,MATCH(A14,'SKU Catalog'!$A$6:$A$21,0)),INDEX('SKU Catalog'!$G$6:$G$21,MATCH(A14,'SKU Catalog'!$A$6:$A$21,0))) -> 850 | D14: 2 | E14: 75 | F14: =D14*E14 -> 150 | G14: 110 | H14: =F14+G14 -> 260 | I14: =C14-H14 -> 590 | J14: =IFERROR(I14/C14,0) -> 0.69411765
A15: PAO-INF-RAG | B15: =INDEX('SKU Catalog'!$C$6:$C$21,MATCH(A15,'SKU Catalog'!$A$6:$A$21,0)) -> Infrastructure Add-on | C15: =AVERAGE(INDEX('SKU Catalog'!$F$6:$F$21,MATCH(A15,'SKU Catalog'!$A$6:$A$21,0)),INDEX('SKU Catalog'!$G$6:$G$21,MATCH(A15,'SKU Catalog'!$A$6:$A$21,0))) -> 1400 | D15: 3 | E15: 75 | F15: =D15*E15 -> 225 | G15: 180 | H15: =F15+G15 -> 405 | I15: =C15-H15 -> 995 | J15: =IFERROR(I15/C15,0) -> 0.71071429
A16: PAO-INF-MGD | B16: =INDEX('SKU Catalog'!$C$6:$C$21,MATCH(A16,'SKU Catalog'!$A$6:$A$21,0)) -> Infrastructure Add-on | C16: =AVERAGE(INDEX('SKU Catalog'!$F$6:$F$21,MATCH(A16,'SKU Catalog'!$A$6:$A$21,0)),INDEX('SKU Catalog'!$G$6:$G$21,MATCH(A16,'SKU Catalog'!$A$6:$A$21,0))) -> 2850 | D16: 4 | E16: 75 | F16: =D16*E16 -> 300 | G16: 260 | H16: =F16+G16 -> 560 | I16: =C16-H16 -> 2290 | J16: =IFERROR(I16/C16,0) -> 0.80350877
A17: PAO-PRO-STD | B17: =INDEX('SKU Catalog'!$C$6:$C$21,MATCH(A17,'SKU Catalog'!$A$6:$A$21,0)) -> Validation Tier | C17: =AVERAGE(INDEX('SKU Catalog'!$F$6:$F$21,MATCH(A17,'SKU Catalog'!$A$6:$A$21,0)),INDEX('SKU Catalog'!$G$6:$G$21,MATCH(A17,'SKU Catalog'!$A$6:$A$21,0))) -> 124 | D17: 0.5 | E17: 75 | F17: =D17*E17 -> 37.5 | G17: 5 | H17: =F17+G17 -> 42.5 | I17: =C17-H17 -> 81.5 | J17: =IFERROR(I17/C17,0) -> 0.65725806
A19: All yellow-highlighted inputs (hours, labor rate, COGS) are founder-supplied assumptions, not measured actuals. Margins here are directional and intended to sanity-check pricing — not a substitute for the full financial model.

Sheet Rate Card (Client-Facing)
A1: PRIVATE AI OPS
A2: Managed AI Operations — Rate Card
A3: Private, secure AI workflows for privacy-sensitive SMBs — pricing effective September 2026
A5: AI Ops Assessment
A6: Standard | B6: $500 – $1,500 | C6: Workflow discovery and automation roadmap for a single-location SMB. Waived if you proceed to onboarding.
A7: Complex / Regulated | B7: $1,500 – $2,500 | C7: For multi-location or regulated practices (law, dental/healthcare). Waived if you proceed to onboarding.
A9: Managed AI Onboarding
A10: Small SMB | B10: $3,500 – $10,000 | C10: Full workflow build-out: process mapping, prompt architecture, tool configuration, staff training, first workflow launch.
A11: Complex / Regulated | B11: $10,000 – $25,000 | C11: Includes BAA/DPA execution and security/access configuration for multi-location or regulated clients.
A13: Managed AI Ops Retainer (monthly)
A14: Small SMB | B14: $1,500 – $3,000 / mo | C14: Ongoing workflow maintenance, prompt tuning, monitoring, reporting, staff support.
A15: Multi-location / Regulated | B15: $3,000 – $7,500 / mo | C15: Adds governance updates and usage analytics across multiple workflows or locations.
A16: Heavy / Custom Environment | B16: $7,500+ / mo | C16: For complex, multi-workflow environments, typically paired with a private infrastructure add-on.
A18: Private AI Infrastructure (add-on to an active Retainer)
A19: Private Endpoint | B19: $650 / mo | C19: Dedicated, isolated inference endpoint.
A20: HIPAA-Ready / BAA-Supported Endpoint | B20: $850 / mo | C20: BAA-supported, audit-friendly endpoint for regulated workflows.
A21: Dual GPU + RAG | B21: $1,400 / mo | C21: Dedicated retrieval-augmented environment for document-heavy workflows.
A22: Managed Private AI Environment | B22: $2,200+ / mo | C22: Highest tier — scoped and priced case-by-case for larger environments.
A24: Try It First
A25: Free vertical tools | B25: Free | C25: Law Brief, Dental Brief, Property Brief, Charter Brief — one narrow workflow, no cost.
A26: Pro Tier | B26: $49 – $199 / mo | C26: Self-serve validation tier tied to a free vertical tool, ahead of a full retainer engagement.
